markdown-stubs/METADATA.toml
markdown-stubs/__init__.pyi
markdown-stubs/__main__.pyi
markdown-stubs/__meta__.pyi
markdown-stubs/blockparser.pyi
markdown-stubs/blockprocessors.pyi
markdown-stubs/core.pyi
markdown-stubs/htmlparser.pyi
markdown-stubs/inlinepatterns.pyi
markdown-stubs/postprocessors.pyi
markdown-stubs/preprocessors.pyi
markdown-stubs/py.typed
markdown-stubs/serializers.pyi
markdown-stubs/test_tools.pyi
markdown-stubs/treeprocessors.pyi
markdown-stubs/util.pyi
markdown-stubs/extensions/__init__.pyi
markdown-stubs/extensions/abbr.pyi
markdown-stubs/extensions/admonition.pyi
markdown-stubs/extensions/attr_list.pyi
markdown-stubs/extensions/codehilite.pyi
markdown-stubs/extensions/def_list.pyi
markdown-stubs/extensions/extra.pyi
markdown-stubs/extensions/fenced_code.pyi
markdown-stubs/extensions/footnotes.pyi
markdown-stubs/extensions/legacy_attrs.pyi
markdown-stubs/extensions/legacy_em.pyi
markdown-stubs/extensions/md_in_html.pyi
markdown-stubs/extensions/meta.pyi
markdown-stubs/extensions/nl2br.pyi
markdown-stubs/extensions/sane_lists.pyi
markdown-stubs/extensions/smarty.pyi
markdown-stubs/extensions/tables.pyi
markdown-stubs/extensions/toc.pyi
markdown-stubs/extensions/wikilinks.pyi
types_markdown-3.8.0.20250809.dist-info/licenses/LICENSE
types_markdown-3.8.0.20250809.dist-info/METADATA
types_markdown-3.8.0.20250809.dist-info/WHEEL
types_markdown-3.8.0.20250809.dist-info/top_level.txt
types_markdown-3.8.0.20250809.dist-info/RECORD
